secops_log_hammer/__init__.py
secops_log_hammer/auth.py
secops_log_hammer/cli.py
secops_log_hammer/client.py
secops_log_hammer/exceptions.py
secops_log_hammer/generators.py
secops_log_hammer/log_ingest.py
secops_log_hammer/templates.py
secops_log_hammer/test/__init__.py
secops_log_hammer/test/test_generators.py
secops_log_hammer-1.2.0.dist-info/licenses/LICENSE
secops_log_hammer-1.2.0.dist-info/METADATA
secops_log_hammer-1.2.0.dist-info/WHEEL
secops_log_hammer-1.2.0.dist-info/entry_points.txt
secops_log_hammer-1.2.0.dist-info/top_level.txt
secops_log_hammer-1.2.0.dist-info/RECORD
