Metadata-Version: 2.4
Name: secops-log-hammer
Version: 1.2.0
Summary: Generate and ingest synthetic logs into Chronicle
Author-email: Google SecOps Team <chronicle@google.com>
License-Expression: Apache-2.0
Project-URL: Homepage, https://github.com/emeryray2002/secops-log-hammer
Project-URL: Bug Tracker, https://github.com/emeryray2002/secops-log-hammer/issues
Keywords: google,security,chronicle,secops
Classifier: Development Status :: 4 - Beta
Classifier: Intended Audience :: Information Technology
Classifier: Intended Audience :: System Administrators
Classifier: Programming Language :: Python :: 3
Classifier: Programming Language :: Python :: 3.7
Classifier: Programming Language :: Python :: 3.8
Classifier: Programming Language :: Python :: 3.9
Classifier: Programming Language :: Python :: 3.10
Classifier: Topic :: Security
Requires-Python: >=3.7
License-File: LICENSE
Requires-Dist: tqdm
Requires-Dist: google-auth
Requires-Dist: google-auth-oauthlib
Requires-Dist: requests
Dynamic: license-file
